EITRI/__init__.py
EITRI/eitri.py
EITRI/utils.py
EITRI/Account/__init__.py
EITRI/Account/account.py
EITRI/Block/__init__.py
EITRI/Block/block.py
EITRI/Network/__init__.py
EITRI/Network/network.py
EITRI/Node/__init__.py
EITRI/Node/node.py
EITRI/Transaction/__init__.py
EITRI/Transaction/transaction.py
EITRI/Validator/__init__.py
EITRI/Validator/validator.py
EITRI-1.9.dist-info/METADATA
EITRI-1.9.dist-info/RECORD
EITRI-1.9.dist-info/WHEEL
EITRI-1.9.dist-info/top_level.txt
