Metadata-Version: 2.1
Name: EITRI
Version: 1.9
Summary: SDK for EITRI Blockchain
Home-page: https://github.com/bitrustkr/CLT-Blockchain-SDK-PY
Author: JeongTae Park
Author-email: pjt3591oo@gmail.com
License: UNKNOWN
Keywords: blockchain,sdk,eitri,EITRI
Platform: UNKNOWN
Classifier: Programming Language :: Python :: 3
Classifier: Programming Language :: Python :: 3.2
Classifier: Programming Language :: Python :: 3.3
Classifier: Programming Language :: Python :: 3.4
Classifier: Programming Language :: Python :: 3.5
Classifier: Programming Language :: Python :: 3.6
Requires-Python: >=3
Requires-Dist: jsonrpc2
